flask_appconfig/__init__.py
flask_appconfig/cli.py
flask_appconfig/env.py
flask_appconfig/heroku.py
flask_appconfig/middleware.py
flask_appconfig/server_backends.py
flask_appconfig/util.py
flask_appconfig_current-0.13.2.dist-info/LICENSE
flask_appconfig_current-0.13.2.dist-info/METADATA
flask_appconfig_current-0.13.2.dist-info/WHEEL
flask_appconfig_current-0.13.2.dist-info/entry_points.txt
flask_appconfig_current-0.13.2.dist-info/top_level.txt
flask_appconfig_current-0.13.2.dist-info/RECORD
