Metadata-Version: 2.1
Name: flask-appconfig-current
Version: 0.13.2
Summary: Configures Flask applications in a canonical way. Also auto-configures Heroku. Aims to standardize configuration.
Home-page: http://github.com/mbr/flask-appconfig
Author: Marc Brinkmann
Author-email: git@marcbrinkmann.de
License: MIT
Classifier: Programming Language :: Python :: 3
License-File: LICENSE
Requires-Dist: flask >=1.0
Requires-Dist: six
Requires-Dist: click
